README.rst
setup.py
rqalpha_mod_incremental/__init__.py
rqalpha_mod_incremental/mod.py
rqalpha_mod_incremental/persist_providers.py
rqalpha_mod_incremental/recorders.py
rqalpha_mod_incremental.egg-info/PKG-INFO
rqalpha_mod_incremental.egg-info/SOURCES.txt
rqalpha_mod_incremental.egg-info/dependency_links.txt
rqalpha_mod_incremental.egg-info/not-zip-safe
rqalpha_mod_incremental.egg-info/requires.txt
rqalpha_mod_incremental.egg-info/top_level.txt