Metadata-Version: 1.0
Name: rqalpha-mod-incremental
Version: 0.0.5a1
Summary: rqalpha-mod-incremental
Home-page: UNKNOWN
Author: ricequant
Author-email: public@ricequant.com
License: Apache License v2
Platform: UNKNOWN
